wx_connector_pysdk/__init__.py
wx_connector_pysdk/models.py
wx_connector_pysdk/py.typed
wx_connector_pysdk-0.1.1.dist-info/METADATA
wx_connector_pysdk-0.1.1.dist-info/WHEEL
wx_connector_pysdk-0.1.1.dist-info/licenses/LICENSE
wx_connector_pysdk-0.1.1.dist-info/RECORD
