Metadata-Version: 2.4
Name: wx-connector-pysdk
Version: 0.1.1
Summary: wx-connector-pysdk 是一个为便捷在python项目中使用WxConnector进行开发而构建的轮子
Author-email: Eliver <Eliver52@outlook.com>
License: AGPL-3.0-only
License-File: LICENSE
Requires-Python: >=3.11
Requires-Dist: requests>=2.32.3
Requires-Dist: websocket-client>=1.8.0
